nn/__init__.py
nn/activations.py
nn/callbacks.py
nn/layers.py
nn/losses.py
nn/models.py
nn/optimizers.py
open_nn_python-0.3.1.dist-info/LICENSE
open_nn_python-0.3.1.dist-info/METADATA
open_nn_python-0.3.1.dist-info/WHEEL
open_nn_python-0.3.1.dist-info/top_level.txt
open_nn_python-0.3.1.dist-info/RECORD
