Metadata-Version: 2.1
Name: open-nn-python
Version: 0.3.1
Summary: A Neural Network implementation from scratch in Python
Home-page: https://github.com/NotShrirang/OpenNN
Author: Shrirang Mahajan
Author-email: shrirangmahajan123@gmail.com
Project-URL: Bug Tracker, https://github.com/NotShrirang/OpenNN/issues
Classifier: Programming Language :: Python :: 3
Classifier: License :: OSI Approved :: MIT License
Classifier: Operating System :: OS Independent
Requires-Python: >=3.6
License-File: LICENSE
